geometer/__init__.py
geometer/base.py
geometer/curve.py
geometer/exceptions.py
geometer/operators.py
geometer/point.py
geometer/py.typed
geometer/shapes.py
geometer/transformation.py
geometer/version.py
geometer/utils/__init__.py
geometer/utils/indexing.py
geometer/utils/math.py
geometer/utils/ops_dispatch.py
geometer/utils/typing.py
geometer-0.4.2.dist-info/METADATA
geometer-0.4.2.dist-info/WHEEL
geometer-0.4.2.dist-info/licenses/LICENSE
geometer-0.4.2.dist-info/RECORD
