Metadata-Version: 2.4
Name: geometer
Version: 0.4.2
Summary: Python geometry package based on projective geometry and numpy.
Project-URL: Changelog, https://github.com/jan-mue/geometer/releases
Project-URL: Documentation, https://github.com/jan-mue/geometer#readme
Project-URL: Issues, https://github.com/jan-mue/geometer/issues
Project-URL: Source, https://github.com/jan-mue/geometer
Author: Jan Müller
License-Expression: MIT
License-File: LICENSE
Keywords: geometry,mathematics,numpy,projective geometry
Classifier: Development Status :: 4 - Beta
Classifier: License :: OSI Approved :: MIT License
Classifier: Programming Language :: Python
Classifier: Programming Language :: Python :: 3 :: Only
Classifier: Programming Language :: Python :: 3.9
Classifier: Programming Language :: Python :: 3.10
Classifier: Programming Language :: Python :: 3.11
Classifier: Programming Language :: Python :: 3.12
Classifier: Programming Language :: Python :: 3.13
Classifier: Programming Language :: Python :: 3.14
Classifier: Programming Language :: Python :: Implementation :: CPython
Classifier: Programming Language :: Python :: Implementation :: PyPy
Requires-Python: >=3.9
Requires-Dist: numpy>=2.0
Requires-Dist: typing-extensions<5.0.0,>=4.6.1
